[
    {
        "material": "Städning",
        "materialid": "0",
        "senaktivitet": "2023-06-22T07:36:01",
        "nastaaktivitet": "2023-06-26T00:00:00"
    },
    {
        "material": "Metallförpackningar",
        "materialid": "3",
        "senaktivitet": "2023-06-02T09:18:25",
        "nastaaktivitet": "2023-07-28T00:00:00"
    },
    {
        "material": "Pappersförpackningar",
        "materialid": "5",
        "senaktivitet": "2023-06-23T07:33:42",
        "nastaaktivitet": "2023-06-26T00:00:00"
    },
    {
        "material": "Tidningar",
        "materialid": "13",
        "senaktivitet": "2023-06-07T17:07:46",
        "nastaaktivitet": null
    },
    {
        "material": "Plastförpackningar",
        "materialid": "16",
        "senaktivitet": "2023-06-22T07:51:29",
        "nastaaktivitet": "2023-06-29T00:00:00"
    },
    {
        "material": "Ofärgade glasförpackningar",
        "materialid": "18",
        "senaktivitet": "2023-05-23T08:04:38",
        "nastaaktivitet": null
    },
    {
        "material": "Färgade glasförpackningar",
        "materialid": "19",
        "senaktivitet": "2023-05-23T08:04:38",
        "nastaaktivitet": null
    }
]