[
    {
        "material": "Städning",
        "materialid": "0",
        "senaktivitet": "2023-04-21T10:16:37",
        "nastaaktivitet": "2023-04-24T00:00:00"
    },
    {
        "material": "Metallförpackningar",
        "materialid": "3",
        "senaktivitet": "2023-03-28T11:31:38",
        "nastaaktivitet": "2023-05-11T00:00:00"
    },
    {
        "material": "Pappersförpackningar",
        "materialid": "5",
        "senaktivitet": "2023-04-22T11:18:21",
        "nastaaktivitet": "2023-04-23T00:00:00"
    },
    {
        "material": "Tidningar",
        "materialid": "13",
        "senaktivitet": "2023-04-18T10:06:08",
        "nastaaktivitet": null
    },
    {
        "material": "Plastförpackningar",
        "materialid": "16",
        "senaktivitet": "2023-04-21T12:36:21",
        "nastaaktivitet": "2023-04-23T00:00:00"
    },
    {
        "material": "Ofärgade glasförpackningar",
        "materialid": "18",
        "senaktivitet": "2023-04-21T18:08:55",
        "nastaaktivitet": null
    },
    {
        "material": "Färgade glasförpackningar",
        "materialid": "19",
        "senaktivitet": "2023-04-21T18:08:55",
        "nastaaktivitet": null
    }
]