[
    {
        "material": "Städning",
        "materialid": "0",
        "senaktivitet": "2022-11-21T16:20:33",
        "nastaaktivitet": "2022-11-23T00:00:00"
    },
    {
        "material": "Metallförpackningar",
        "materialid": "3",
        "senaktivitet": "2022-11-02T15:59:27",
        "nastaaktivitet": "2022-12-28T00:00:00"
    },
    {
        "material": "Pappersförpackningar",
        "materialid": "5",
        "senaktivitet": "2022-11-21T21:12:21",
        "nastaaktivitet": "2022-11-23T00:00:00"
    },
    {
        "material": "Tidningar",
        "materialid": "13",
        "senaktivitet": "2022-08-04T13:45:09",
        "nastaaktivitet": null
    },
    {
        "material": "Plastförpackningar",
        "materialid": "16",
        "senaktivitet": "2022-11-19T06:26:15",
        "nastaaktivitet": "2022-11-22T00:00:00"
    },
    {
        "material": "Ofärgade glasförpackningar",
        "materialid": "18",
        "senaktivitet": "2022-11-10T12:06:30",
        "nastaaktivitet": null
    },
    {
        "material": "Färgade glasförpackningar",
        "materialid": "19",
        "senaktivitet": "2022-11-10T12:06:30",
        "nastaaktivitet": null
    }
]