[
    {
        "material": "Städning",
        "materialid": "0",
        "senaktivitet": "2023-12-28T08:22:01",
        "nastaaktivitet": null
    },
    {
        "material": "Metallförpackningar",
        "materialid": "3",
        "senaktivitet": "2023-12-25T08:05:48",
        "nastaaktivitet": null
    },
    {
        "material": "Pappersförpackningar",
        "materialid": "5",
        "senaktivitet": "2023-12-26T12:46:53",
        "nastaaktivitet": "2024-05-14T00:00:00"
    },
    {
        "material": "Tidningar",
        "materialid": "13",
        "senaktivitet": "2023-11-28T12:40:45",
        "nastaaktivitet": null
    },
    {
        "material": "Plastförpackningar",
        "materialid": "16",
        "senaktivitet": "2023-12-27T17:22:58",
        "nastaaktivitet": null
    },
    {
        "material": "Ofärgade glasförpackningar",
        "materialid": "18",
        "senaktivitet": "2023-09-14T14:58:56",
        "nastaaktivitet": null
    },
    {
        "material": "Färgade glasförpackningar",
        "materialid": "19",
        "senaktivitet": "2023-09-14T14:58:56",
        "nastaaktivitet": null
    }
]