[
    {
        "material": "Städning",
        "materialid": "0",
        "senaktivitet": "2022-11-21T09:43:16",
        "nastaaktivitet": "2022-11-28T00:00:00"
    },
    {
        "material": "Metallförpackningar",
        "materialid": "3",
        "senaktivitet": "2022-08-18T14:29:20",
        "nastaaktivitet": "2022-12-22T00:00:00"
    },
    {
        "material": "Pappersförpackningar",
        "materialid": "5",
        "senaktivitet": "2022-11-27T09:46:14",
        "nastaaktivitet": "2022-12-04T00:00:00"
    },
    {
        "material": "Tidningar",
        "materialid": "13",
        "senaktivitet": "2022-11-20T18:01:14",
        "nastaaktivitet": null
    },
    {
        "material": "Plastförpackningar",
        "materialid": "16",
        "senaktivitet": "2022-11-26T18:52:21",
        "nastaaktivitet": "2022-12-10T00:00:00"
    },
    {
        "material": "Ofärgade glasförpackningar",
        "materialid": "18",
        "senaktivitet": "2022-11-05T18:11:06",
        "nastaaktivitet": null
    },
    {
        "material": "Färgade glasförpackningar",
        "materialid": "19",
        "senaktivitet": "2022-11-05T18:11:06",
        "nastaaktivitet": null
    }
]