[
    {
        "material": "Städning",
        "materialid": "0",
        "senaktivitet": "2023-05-23T07:37:37",
        "nastaaktivitet": "2023-05-28T00:00:00"
    },
    {
        "material": "Metallförpackningar",
        "materialid": "3",
        "senaktivitet": "2023-05-17T08:04:34",
        "nastaaktivitet": "2023-06-29T00:00:00"
    },
    {
        "material": "Pappersförpackningar",
        "materialid": "5",
        "senaktivitet": "2023-05-25T09:29:01",
        "nastaaktivitet": "2023-05-27T00:00:00"
    },
    {
        "material": "Tidningar",
        "materialid": "13",
        "senaktivitet": "2023-05-22T18:52:10",
        "nastaaktivitet": null
    },
    {
        "material": "Plastförpackningar",
        "materialid": "16",
        "senaktivitet": "2023-05-26T16:33:14",
        "nastaaktivitet": "2023-05-28T00:00:00"
    },
    {
        "material": "Ofärgade glasförpackningar",
        "materialid": "18",
        "senaktivitet": "2023-05-16T16:11:19",
        "nastaaktivitet": null
    },
    {
        "material": "Färgade glasförpackningar",
        "materialid": "19",
        "senaktivitet": "2023-05-16T16:11:19",
        "nastaaktivitet": null
    }
]