[
    {
        "material": "Städning",
        "materialid": "0",
        "senaktivitet": "2023-07-25T11:16:17",
        "nastaaktivitet": "2023-07-28T00:00:00"
    },
    {
        "material": "Metallförpackningar",
        "materialid": "3",
        "senaktivitet": "2023-07-17T18:35:30",
        "nastaaktivitet": "2023-08-01T00:00:00"
    },
    {
        "material": "Pappersförpackningar",
        "materialid": "5",
        "senaktivitet": "2023-07-26T14:09:20",
        "nastaaktivitet": "2023-07-28T00:00:00"
    },
    {
        "material": "Tidningar",
        "materialid": "13",
        "senaktivitet": "2022-05-24T13:26:24",
        "nastaaktivitet": null
    },
    {
        "material": "Plastförpackningar",
        "materialid": "16",
        "senaktivitet": "2023-07-25T16:11:01",
        "nastaaktivitet": "2023-07-29T00:00:00"
    },
    {
        "material": "Ofärgade glasförpackningar",
        "materialid": "18",
        "senaktivitet": "2023-07-08T10:26:54",
        "nastaaktivitet": null
    },
    {
        "material": "Färgade glasförpackningar",
        "materialid": "19",
        "senaktivitet": "2023-07-08T10:26:54",
        "nastaaktivitet": null
    }
]