[
    {
        "material": "Städning",
        "materialid": "0",
        "senaktivitet": "2023-06-02T07:23:57",
        "nastaaktivitet": "2023-06-06T00:00:00"
    },
    {
        "material": "Metallförpackningar",
        "materialid": "3",
        "senaktivitet": "2023-05-23T08:01:52",
        "nastaaktivitet": "2023-07-06T00:00:00"
    },
    {
        "material": "Pappersförpackningar",
        "materialid": "5",
        "senaktivitet": "2023-06-05T06:53:38",
        "nastaaktivitet": "2023-06-07T00:00:00"
    },
    {
        "material": "Tidningar",
        "materialid": "13",
        "senaktivitet": "2023-05-23T16:51:21",
        "nastaaktivitet": null
    },
    {
        "material": "Plastförpackningar",
        "materialid": "16",
        "senaktivitet": "2023-06-05T15:03:49",
        "nastaaktivitet": "2023-06-09T00:00:00"
    },
    {
        "material": "Ofärgade glasförpackningar",
        "materialid": "18",
        "senaktivitet": "2023-05-24T19:54:39",
        "nastaaktivitet": null
    },
    {
        "material": "Färgade glasförpackningar",
        "materialid": "19",
        "senaktivitet": "2023-05-24T19:54:39",
        "nastaaktivitet": null
    }
]