[
    {
        "material": "Städning",
        "materialid": "0",
        "senaktivitet": "2023-05-07T07:52:52",
        "nastaaktivitet": "2023-05-09T00:00:00"
    },
    {
        "material": "Metallförpackningar",
        "materialid": "3",
        "senaktivitet": "2023-04-30T17:12:58",
        "nastaaktivitet": "2023-05-11T00:00:00"
    },
    {
        "material": "Pappersförpackningar",
        "materialid": "5",
        "senaktivitet": "2023-05-08T10:10:24",
        "nastaaktivitet": "2023-05-09T00:00:00"
    },
    {
        "material": "Tidningar",
        "materialid": "13",
        "senaktivitet": "2023-04-25T11:45:59",
        "nastaaktivitet": null
    },
    {
        "material": "Plastförpackningar",
        "materialid": "16",
        "senaktivitet": "2023-05-08T19:10:17",
        "nastaaktivitet": "2023-05-10T00:00:00"
    },
    {
        "material": "Ofärgade glasförpackningar",
        "materialid": "18",
        "senaktivitet": "2023-05-04T16:05:56",
        "nastaaktivitet": null
    },
    {
        "material": "Färgade glasförpackningar",
        "materialid": "19",
        "senaktivitet": "2023-05-04T16:05:56",
        "nastaaktivitet": null
    }
]