[
    {
        "material": "Städning",
        "materialid": "0",
        "senaktivitet": "2022-11-16T13:13:35",
        "nastaaktivitet": "2022-11-23T00:00:00"
    },
    {
        "material": "Metallförpackningar",
        "materialid": "3",
        "senaktivitet": "2022-11-17T09:43:45",
        "nastaaktivitet": "2022-12-15T00:00:00"
    },
    {
        "material": "Pappersförpackningar",
        "materialid": "5",
        "senaktivitet": "2022-11-19T09:10:25",
        "nastaaktivitet": "2022-11-21T00:00:00"
    },
    {
        "material": "Tidningar",
        "materialid": "13",
        "senaktivitet": "2022-01-09T18:15:11",
        "nastaaktivitet": null
    },
    {
        "material": "Plastförpackningar",
        "materialid": "16",
        "senaktivitet": "2022-11-15T09:10:46",
        "nastaaktivitet": "2022-11-22T00:00:00"
    },
    {
        "material": "Ofärgade glasförpackningar",
        "materialid": "18",
        "senaktivitet": "2022-11-08T10:45:28",
        "nastaaktivitet": null
    },
    {
        "material": "Färgade glasförpackningar",
        "materialid": "19",
        "senaktivitet": "2022-11-08T10:45:28",
        "nastaaktivitet": null
    }
]