[
    {
        "material": "Städning",
        "materialid": "0",
        "senaktivitet": "2023-11-23T13:43:00",
        "nastaaktivitet": "2023-12-04T00:00:00"
    },
    {
        "material": "Metallförpackningar",
        "materialid": "3",
        "senaktivitet": "2023-11-01T10:40:58",
        "nastaaktivitet": "2023-12-13T00:00:00"
    },
    {
        "material": "Pappersförpackningar",
        "materialid": "5",
        "senaktivitet": "2023-12-03T10:08:07",
        "nastaaktivitet": "2023-12-05T00:00:00"
    },
    {
        "material": "Tidningar",
        "materialid": "13",
        "senaktivitet": "2023-07-25T09:50:21",
        "nastaaktivitet": null
    },
    {
        "material": "Plastförpackningar",
        "materialid": "16",
        "senaktivitet": "2023-12-03T20:22:17",
        "nastaaktivitet": "2023-12-04T00:00:00"
    },
    {
        "material": "Ofärgade glasförpackningar",
        "materialid": "18",
        "senaktivitet": "2023-11-14T15:24:47",
        "nastaaktivitet": null
    },
    {
        "material": "Färgade glasförpackningar",
        "materialid": "19",
        "senaktivitet": "2023-11-14T15:24:47",
        "nastaaktivitet": null
    }
]