[
    {
        "material": "Städning",
        "materialid": "0",
        "senaktivitet": null,
        "nastaaktivitet": null
    },
    {
        "material": "Metallförpackningar",
        "materialid": "3",
        "senaktivitet": "2022-11-24T08:59:43",
        "nastaaktivitet": "2023-01-19T00:00:00"
    },
    {
        "material": "Pappersförpackningar",
        "materialid": "5",
        "senaktivitet": "2023-01-02T08:22:10",
        "nastaaktivitet": "2023-01-04T00:00:00"
    },
    {
        "material": "Tidningar",
        "materialid": "13",
        "senaktivitet": "2022-11-16T07:49:30",
        "nastaaktivitet": null
    },
    {
        "material": "Plastförpackningar",
        "materialid": "16",
        "senaktivitet": "2023-01-02T08:21:13",
        "nastaaktivitet": "2023-01-05T00:00:00"
    },
    {
        "material": "Ofärgade glasförpackningar",
        "materialid": "18",
        "senaktivitet": "2022-12-09T08:08:55",
        "nastaaktivitet": null
    },
    {
        "material": "Färgade glasförpackningar",
        "materialid": "19",
        "senaktivitet": "2022-12-09T08:08:55",
        "nastaaktivitet": null
    }
]