[
    {
        "material": "Städning",
        "materialid": "0",
        "senaktivitet": "2022-11-02T16:43:26",
        "nastaaktivitet": "2022-11-09T00:00:00"
    },
    {
        "material": "Metallförpackningar",
        "materialid": "3",
        "senaktivitet": "2022-10-25T11:09:57",
        "nastaaktivitet": "2022-11-22T00:00:00"
    },
    {
        "material": "Pappersförpackningar",
        "materialid": "5",
        "senaktivitet": "2022-11-01T09:53:42",
        "nastaaktivitet": "2022-11-03T00:00:00"
    },
    {
        "material": "Tidningar",
        "materialid": "13",
        "senaktivitet": "2022-10-26T18:12:35",
        "nastaaktivitet": null
    },
    {
        "material": "Plastförpackningar",
        "materialid": "16",
        "senaktivitet": "2022-11-02T14:13:11",
        "nastaaktivitet": "2022-11-06T00:00:00"
    },
    {
        "material": "Ofärgade glasförpackningar",
        "materialid": "18",
        "senaktivitet": "2022-10-28T16:31:38",
        "nastaaktivitet": null
    },
    {
        "material": "Färgade glasförpackningar",
        "materialid": "19",
        "senaktivitet": "2022-10-28T16:31:38",
        "nastaaktivitet": null
    }
]