[
    {
        "material": "Städning",
        "materialid": "0",
        "senaktivitet": "2023-03-16T18:22:06",
        "nastaaktivitet": "2023-03-18T00:00:00"
    },
    {
        "material": "Metallförpackningar",
        "materialid": "3",
        "senaktivitet": "2023-03-10T11:04:23",
        "nastaaktivitet": "2023-03-23T00:00:00"
    },
    {
        "material": "Pappersförpackningar",
        "materialid": "5",
        "senaktivitet": "2023-03-17T11:46:42",
        "nastaaktivitet": "2023-03-18T00:00:00"
    },
    {
        "material": "Tidningar",
        "materialid": "13",
        "senaktivitet": "2023-03-17T10:56:54",
        "nastaaktivitet": null
    },
    {
        "material": "Plastförpackningar",
        "materialid": "16",
        "senaktivitet": "2023-03-16T06:39:39",
        "nastaaktivitet": "2023-03-19T00:00:00"
    },
    {
        "material": "Ofärgade glasförpackningar",
        "materialid": "18",
        "senaktivitet": "2023-03-13T10:50:39",
        "nastaaktivitet": null
    },
    {
        "material": "Färgade glasförpackningar",
        "materialid": "19",
        "senaktivitet": "2023-03-13T10:50:39",
        "nastaaktivitet": null
    }
]