[
    {
        "material": "Städning",
        "materialid": "0",
        "senaktivitet": "2023-08-11T09:14:42",
        "nastaaktivitet": "2023-08-15T00:00:00"
    },
    {
        "material": "Metallförpackningar",
        "materialid": "3",
        "senaktivitet": "2023-07-04T12:49:57",
        "nastaaktivitet": "2023-09-26T00:00:00"
    },
    {
        "material": "Pappersförpackningar",
        "materialid": "5",
        "senaktivitet": "2023-08-14T08:02:26",
        "nastaaktivitet": "2023-08-18T00:00:00"
    },
    {
        "material": "Tidningar",
        "materialid": "13",
        "senaktivitet": null,
        "nastaaktivitet": null
    },
    {
        "material": "Plastförpackningar",
        "materialid": "16",
        "senaktivitet": "2023-08-13T13:36:41",
        "nastaaktivitet": "2023-08-16T00:00:00"
    },
    {
        "material": "Ofärgade glasförpackningar",
        "materialid": "18",
        "senaktivitet": "2023-08-03T21:31:50",
        "nastaaktivitet": null
    },
    {
        "material": "Färgade glasförpackningar",
        "materialid": "19",
        "senaktivitet": "2023-08-03T21:31:50",
        "nastaaktivitet": null
    }
]