[
    {
        "material": "Städning",
        "materialid": "0",
        "senaktivitet": "2023-06-25T11:46:56",
        "nastaaktivitet": "2023-06-26T00:00:00"
    },
    {
        "material": "Metallförpackningar",
        "materialid": "3",
        "senaktivitet": "2023-06-21T13:07:09",
        "nastaaktivitet": "2023-07-12T00:00:00"
    },
    {
        "material": "Pappersförpackningar",
        "materialid": "5",
        "senaktivitet": "2023-06-25T06:25:35",
        "nastaaktivitet": "2023-06-26T00:00:00"
    },
    {
        "material": "Tidningar",
        "materialid": "13",
        "senaktivitet": "2023-05-29T10:34:09",
        "nastaaktivitet": null
    },
    {
        "material": "Plastförpackningar",
        "materialid": "16",
        "senaktivitet": "2023-06-25T17:51:38",
        "nastaaktivitet": "2023-06-27T00:00:00"
    },
    {
        "material": "Ofärgade glasförpackningar",
        "materialid": "18",
        "senaktivitet": "2023-06-18T17:21:48",
        "nastaaktivitet": null
    },
    {
        "material": "Färgade glasförpackningar",
        "materialid": "19",
        "senaktivitet": "2023-06-18T17:21:48",
        "nastaaktivitet": null
    }
]