[
    {
        "material": "Städning",
        "materialid": "0",
        "senaktivitet": "2023-04-07T09:20:22",
        "nastaaktivitet": "2023-04-10T00:00:00"
    },
    {
        "material": "Metallförpackningar",
        "materialid": "3",
        "senaktivitet": "2023-04-05T18:10:30",
        "nastaaktivitet": "2023-05-04T00:00:00"
    },
    {
        "material": "Pappersförpackningar",
        "materialid": "5",
        "senaktivitet": "2023-04-08T15:20:40",
        "nastaaktivitet": "2023-04-09T00:00:00"
    },
    {
        "material": "Tidningar",
        "materialid": "13",
        "senaktivitet": "2023-04-04T08:06:37",
        "nastaaktivitet": null
    },
    {
        "material": "Plastförpackningar",
        "materialid": "16",
        "senaktivitet": "2023-04-07T10:01:13",
        "nastaaktivitet": "2023-04-09T00:00:00"
    },
    {
        "material": "Ofärgade glasförpackningar",
        "materialid": "18",
        "senaktivitet": "2023-04-07T13:28:21",
        "nastaaktivitet": null
    },
    {
        "material": "Färgade glasförpackningar",
        "materialid": "19",
        "senaktivitet": "2023-04-07T13:28:21",
        "nastaaktivitet": null
    }
]