[
    {
        "material": "Städning",
        "materialid": "0",
        "senaktivitet": "2022-11-11T09:24:07",
        "nastaaktivitet": "2022-11-13T00:00:00"
    },
    {
        "material": "Metallförpackningar",
        "materialid": "3",
        "senaktivitet": "2022-11-09T09:44:24",
        "nastaaktivitet": "2022-11-14T00:00:00"
    },
    {
        "material": "Pappersförpackningar",
        "materialid": "5",
        "senaktivitet": "2022-11-11T15:14:55",
        "nastaaktivitet": "2022-11-12T00:00:00"
    },
    {
        "material": "Tidningar",
        "materialid": "13",
        "senaktivitet": null,
        "nastaaktivitet": null
    },
    {
        "material": "Plastförpackningar",
        "materialid": "16",
        "senaktivitet": "2022-11-11T08:02:09",
        "nastaaktivitet": "2022-11-12T00:00:00"
    },
    {
        "material": "Ofärgade glasförpackningar",
        "materialid": "18",
        "senaktivitet": "2022-11-10T15:42:28",
        "nastaaktivitet": null
    },
    {
        "material": "Färgade glasförpackningar",
        "materialid": "19",
        "senaktivitet": "2022-11-10T15:42:28",
        "nastaaktivitet": null
    }
]