[
    {
        "material": "Städning",
        "materialid": "0",
        "senaktivitet": "2023-12-26T11:22:05",
        "nastaaktivitet": null
    },
    {
        "material": "Metallförpackningar",
        "materialid": "3",
        "senaktivitet": "2023-12-14T10:26:45",
        "nastaaktivitet": null
    },
    {
        "material": "Pappersförpackningar",
        "materialid": "5",
        "senaktivitet": "2023-12-30T13:29:41",
        "nastaaktivitet": null
    },
    {
        "material": "Tidningar",
        "materialid": "13",
        "senaktivitet": "2023-12-18T13:22:42",
        "nastaaktivitet": null
    },
    {
        "material": "Plastförpackningar",
        "materialid": "16",
        "senaktivitet": "2023-12-29T14:50:44",
        "nastaaktivitet": null
    },
    {
        "material": "Ofärgade glasförpackningar",
        "materialid": "18",
        "senaktivitet": "2023-12-22T14:01:42",
        "nastaaktivitet": null
    },
    {
        "material": "Färgade glasförpackningar",
        "materialid": "19",
        "senaktivitet": "2023-12-22T14:01:42",
        "nastaaktivitet": null
    }
]