[
    {
        "material": "Städning",
        "materialid": "0",
        "senaktivitet": "2023-12-29T13:19:58",
        "nastaaktivitet": null
    },
    {
        "material": "Metallförpackningar",
        "materialid": "3",
        "senaktivitet": "2023-12-10T10:59:02",
        "nastaaktivitet": "2024-05-26T00:00:00"
    },
    {
        "material": "Pappersförpackningar",
        "materialid": "5",
        "senaktivitet": "2023-12-31T13:07:22",
        "nastaaktivitet": "2024-05-19T00:00:00"
    },
    {
        "material": "Tidningar",
        "materialid": "13",
        "senaktivitet": "2023-09-28T09:51:54",
        "nastaaktivitet": null
    },
    {
        "material": "Plastförpackningar",
        "materialid": "16",
        "senaktivitet": "2023-12-29T10:20:31",
        "nastaaktivitet": null
    },
    {
        "material": "Ofärgade glasförpackningar",
        "materialid": "18",
        "senaktivitet": "2023-12-19T11:21:37",
        "nastaaktivitet": null
    },
    {
        "material": "Färgade glasförpackningar",
        "materialid": "19",
        "senaktivitet": "2023-12-19T11:21:37",
        "nastaaktivitet": null
    }
]