[
    {
        "material": "Städning",
        "materialid": "0",
        "senaktivitet": "2023-03-10T11:14:54",
        "nastaaktivitet": "2023-03-13T00:00:00"
    },
    {
        "material": "Metallförpackningar",
        "materialid": "3",
        "senaktivitet": "2023-02-22T07:44:42",
        "nastaaktivitet": "2023-04-19T00:00:00"
    },
    {
        "material": "Pappersförpackningar",
        "materialid": "5",
        "senaktivitet": "2023-03-10T12:02:32",
        "nastaaktivitet": "2023-03-12T00:00:00"
    },
    {
        "material": "Tidningar",
        "materialid": "13",
        "senaktivitet": null,
        "nastaaktivitet": null
    },
    {
        "material": "Plastförpackningar",
        "materialid": "16",
        "senaktivitet": "2023-03-09T14:01:46",
        "nastaaktivitet": "2023-03-13T00:00:00"
    },
    {
        "material": "Ofärgade glasförpackningar",
        "materialid": "18",
        "senaktivitet": "2023-02-28T08:34:02",
        "nastaaktivitet": null
    },
    {
        "material": "Färgade glasförpackningar",
        "materialid": "19",
        "senaktivitet": "2023-02-28T08:34:02",
        "nastaaktivitet": null
    }
]