[
    {
        "material": "Städning",
        "materialid": "0",
        "senaktivitet": "2022-12-13T10:15:04",
        "nastaaktivitet": "2022-12-15T00:00:00"
    },
    {
        "material": "Metallförpackningar",
        "materialid": "3",
        "senaktivitet": "2022-12-01T08:11:33",
        "nastaaktivitet": "2022-12-15T00:00:00"
    },
    {
        "material": "Pappersförpackningar",
        "materialid": "5",
        "senaktivitet": "2022-12-13T09:33:22",
        "nastaaktivitet": "2022-12-14T00:00:00"
    },
    {
        "material": "Tidningar",
        "materialid": "13",
        "senaktivitet": "2022-12-07T08:08:00",
        "nastaaktivitet": null
    },
    {
        "material": "Plastförpackningar",
        "materialid": "16",
        "senaktivitet": "2022-12-13T15:54:41",
        "nastaaktivitet": "2022-12-15T00:00:00"
    },
    {
        "material": "Ofärgade glasförpackningar",
        "materialid": "18",
        "senaktivitet": "2022-12-06T10:05:29",
        "nastaaktivitet": null
    },
    {
        "material": "Färgade glasförpackningar",
        "materialid": "19",
        "senaktivitet": "2022-12-06T10:05:29",
        "nastaaktivitet": null
    }
]