[
    {
        "material": "Städning",
        "materialid": "0",
        "senaktivitet": "2023-01-02T14:34:01",
        "nastaaktivitet": "2023-01-05T00:00:00"
    },
    {
        "material": "Metallförpackningar",
        "materialid": "3",
        "senaktivitet": "2023-01-03T09:36:37",
        "nastaaktivitet": "2023-01-04T00:00:00"
    },
    {
        "material": "Pappersförpackningar",
        "materialid": "5",
        "senaktivitet": "2023-01-02T07:56:53",
        "nastaaktivitet": "2023-01-04T00:00:00"
    },
    {
        "material": "Tidningar",
        "materialid": "13",
        "senaktivitet": null,
        "nastaaktivitet": null
    },
    {
        "material": "Plastförpackningar",
        "materialid": "16",
        "senaktivitet": "2022-12-28T08:54:39",
        "nastaaktivitet": "2023-01-04T00:00:00"
    },
    {
        "material": "Ofärgade glasförpackningar",
        "materialid": "18",
        "senaktivitet": "2022-12-29T09:08:41",
        "nastaaktivitet": null
    },
    {
        "material": "Färgade glasförpackningar",
        "materialid": "19",
        "senaktivitet": "2022-12-29T09:08:41",
        "nastaaktivitet": null
    }
]