[
    {
        "material": "Städning",
        "materialid": "0",
        "senaktivitet": "2022-11-12T09:56:16",
        "nastaaktivitet": "2022-11-14T00:00:00"
    },
    {
        "material": "Metallförpackningar",
        "materialid": "3",
        "senaktivitet": "2022-11-01T13:04:02",
        "nastaaktivitet": "2022-11-29T00:00:00"
    },
    {
        "material": "Pappersförpackningar",
        "materialid": "5",
        "senaktivitet": "2022-11-13T12:28:26",
        "nastaaktivitet": "2022-11-14T00:00:00"
    },
    {
        "material": "Tidningar",
        "materialid": "13",
        "senaktivitet": "2022-11-07T11:19:04",
        "nastaaktivitet": null
    },
    {
        "material": "Plastförpackningar",
        "materialid": "16",
        "senaktivitet": "2022-11-12T09:23:13",
        "nastaaktivitet": "2022-11-14T00:00:00"
    },
    {
        "material": "Ofärgade glasförpackningar",
        "materialid": "18",
        "senaktivitet": "2022-11-11T07:41:12",
        "nastaaktivitet": null
    },
    {
        "material": "Färgade glasförpackningar",
        "materialid": "19",
        "senaktivitet": "2022-11-11T07:41:12",
        "nastaaktivitet": null
    }
]