[
    {
        "material": "Städning",
        "materialid": "0",
        "senaktivitet": "2023-11-23T09:58:44",
        "nastaaktivitet": "2023-11-28T00:00:00"
    },
    {
        "material": "Metallförpackningar",
        "materialid": "3",
        "senaktivitet": "2023-10-16T11:50:20",
        "nastaaktivitet": "2023-12-14T00:00:00"
    },
    {
        "material": "Pappersförpackningar",
        "materialid": "5",
        "senaktivitet": "2023-11-23T10:32:36",
        "nastaaktivitet": "2023-11-25T00:00:00"
    },
    {
        "material": "Tidningar",
        "materialid": "13",
        "senaktivitet": "2023-10-23T13:27:58",
        "nastaaktivitet": null
    },
    {
        "material": "Plastförpackningar",
        "materialid": "16",
        "senaktivitet": "2023-11-23T08:29:42",
        "nastaaktivitet": "2023-12-07T00:00:00"
    },
    {
        "material": "Ofärgade glasförpackningar",
        "materialid": "18",
        "senaktivitet": "2023-01-03T10:04:02",
        "nastaaktivitet": null
    },
    {
        "material": "Färgade glasförpackningar",
        "materialid": "19",
        "senaktivitet": "2023-01-03T10:04:02",
        "nastaaktivitet": null
    }
]