[
    {
        "material": "Städning",
        "materialid": "0",
        "senaktivitet": "2023-11-15T08:40:04",
        "nastaaktivitet": "2023-11-20T00:00:00"
    },
    {
        "material": "Metallförpackningar",
        "materialid": "3",
        "senaktivitet": "2023-09-27T08:54:27",
        "nastaaktivitet": null
    },
    {
        "material": "Pappersförpackningar",
        "materialid": "5",
        "senaktivitet": "2023-11-16T09:56:36",
        "nastaaktivitet": "2023-11-23T00:00:00"
    },
    {
        "material": "Tidningar",
        "materialid": "13",
        "senaktivitet": "2023-05-31T11:02:22",
        "nastaaktivitet": null
    },
    {
        "material": "Plastförpackningar",
        "materialid": "16",
        "senaktivitet": "2023-11-14T10:07:38",
        "nastaaktivitet": "2023-11-21T00:00:00"
    },
    {
        "material": "Ofärgade glasförpackningar",
        "materialid": "18",
        "senaktivitet": "2023-10-04T07:54:02",
        "nastaaktivitet": null
    },
    {
        "material": "Färgade glasförpackningar",
        "materialid": "19",
        "senaktivitet": "2023-10-04T07:54:02",
        "nastaaktivitet": null
    }
]